utsc/core/__init__.py
utsc/core/__main__.py
utsc/core/aruba.py
utsc/core/nested_data.py
utsc/core/other.py
utsc/core/_vendor/__init__.py
utsc/core/_vendor/decorator.py
utsc/core/_vendor/bluecat_libraries/__init__.py
utsc/core/_vendor/bluecat_libraries/address_manager/__init__.py
utsc/core/_vendor/bluecat_libraries/address_manager/_graphql/__init__.py
utsc/core/_vendor/bluecat_libraries/address_manager/_graphql/client.py
utsc/core/_vendor/bluecat_libraries/address_manager/_graphql/exceptions.py
utsc/core/_vendor/bluecat_libraries/address_manager/api/__init__.py
utsc/core/_vendor/bluecat_libraries/address_manager/api/_version.py
utsc/core/_vendor/bluecat_libraries/address_manager/api/client.py
utsc/core/_vendor/bluecat_libraries/address_manager/api/models.py
utsc/core/_vendor/bluecat_libraries/address_manager/api/serialization.py
utsc/core/_vendor/bluecat_libraries/address_manager/api/rest/__init__.py
utsc/core/_vendor/bluecat_libraries/address_manager/api/rest/auto/__init__.py
utsc/core/_vendor/bluecat_libraries/address_manager/api/rest/auto/_wadl_parser.py
utsc/core/_vendor/bluecat_libraries/address_manager/api/rest/auto/client.py
utsc/core/_vendor/bluecat_libraries/address_manager/api/rest/provisional/__init__.py
utsc/core/_vendor/bluecat_libraries/address_manager/api/rest/provisional/client.py
utsc/core/_vendor/bluecat_libraries/address_manager/api/rest/provisional/rest_dict.py
utsc/core/_vendor/bluecat_libraries/address_manager/api/rest/provisional/rest_entity_array.py
utsc/core/_vendor/bluecat_libraries/address_manager/api/rest/provisional/rest_fault.py
utsc/core/_vendor/bluecat_libraries/address_manager/constants/__init__.py
utsc/core/_vendor/bluecat_libraries/address_manager/constants/_enum.py
utsc/core/_vendor/bluecat_libraries/address_manager/constants/_version.py
utsc/core/_vendor/bluecat_libraries/address_manager/constants/access_right_values.py
utsc/core/_vendor/bluecat_libraries/address_manager/constants/additional_ip_service_type.py
utsc_core-2022.5.27.dist-info/METADATA
utsc_core-2022.5.27.dist-info/WHEEL
utsc_core-2022.5.27.dist-info/entry_points.txt
utsc_core-2022.5.27.dist-info/RECORD
